pointsecio/__init__.py
pointsecio/__main__.py
pointsecio/auditor.py
pointsecio/cli.py
pointsecio/exceptions.py
pointsecio/flusher.py
pointsecio/handlers.py
pointsecio/http_facts.py
pointsecio/json_schema.py
pointsecio/jsonifier.py
pointsecio/lifecycle.py
pointsecio/logger.py
pointsecio/mock.py
pointsecio/options.py
pointsecio/problem.py
pointsecio/resolver.py
pointsecio/sender.py
pointsecio/spec.py
pointsecio/utils.py
pointsecio/apis/__init__.py
pointsecio/apis/abstract.py
pointsecio/apis/flask_api.py
pointsecio/apis/flask_utils.py
pointsecio/apps/__init__.py
pointsecio/apps/abstract.py
pointsecio/apps/flask_app.py
pointsecio/decorators/__init__.py
pointsecio/decorators/coroutine_wrappers.py
pointsecio/decorators/decorator.py
pointsecio/decorators/metrics.py
pointsecio/decorators/parameter.py
pointsecio/decorators/produces.py
pointsecio/decorators/response.py
pointsecio/decorators/uri_parsing.py
pointsecio/decorators/validation.py
pointsecio/middleware/__init__.py
pointsecio/middleware/base.py
pointsecio/middleware/main.py
pointsecio/middleware/swagger_ui.py
pointsecio/operations/__init__.py
pointsecio/operations/abstract.py
pointsecio/operations/compat.py
pointsecio/operations/openapi.py
pointsecio/operations/secure.py
pointsecio/operations/swagger2.py
pointsecio/resources/schemas/v2.0/schema.json
pointsecio/resources/schemas/v3.0/schema.json
pointsecio/security/__init__.py
pointsecio/security/async_security_handler_factory.py
pointsecio/security/flask_security_handler_factory.py
pointsecio/security/security_handler_factory.py
pointsecio-1.0.2.dist-info/LICENSE.txt
pointsecio-1.0.2.dist-info/METADATA
pointsecio-1.0.2.dist-info/WHEEL
pointsecio-1.0.2.dist-info/entry_points.txt
pointsecio-1.0.2.dist-info/top_level.txt
pointsecio-1.0.2.dist-info/RECORD
