Metadata-Version: 2.1
Name: pointsecio
Version: 1.0.2
Summary: PointSecIO - API first applications with OpenAPI/Swagger and Flask
Home-page: https://github.com/PointSec-io/pointsecio
Author: point security inc
License: LGPLv3
Keywords: openapi oai swagger rest api oauth flask microservice framework
Platform: UNKNOWN
Classifier: Programming Language :: Python
Classifier: Programming Language :: Python :: 3.7
Classifier: Programming Language :: Python :: 3.8
Classifier: Programming Language :: Python :: 3.9
Classifier: Programming Language :: Python :: 3.10
Classifier: Development Status :: 5 - Production/Stable
Classifier: Intended Audience :: Developers
Classifier: Operating System :: OS Independent
Classifier: Topic :: Internet :: WWW/HTTP :: WSGI :: Application
Classifier: Topic :: Software Development :: Libraries :: Application Frameworks
Requires-Python: >=3.6
License-File: LICENSE.txt
Requires-Dist: clickclick (<21,>=1.2)
Requires-Dist: jsonschema (<5,>=2.5.1)
Requires-Dist: PyYAML (<7,>=5.1)
Requires-Dist: requests (<3,>=2.27)
Requires-Dist: inflection (<0.6,>=0.3.1)
Requires-Dist: werkzeug (<3,>=2)
Requires-Dist: packaging (>=20)
Requires-Dist: starlette (<1,>=0.15)
Requires-Dist: flask (<3,>=2)
Requires-Dist: a2wsgi (<2,>=1.1)
Requires-Dist: importlib-metadata (>=1) ; python_version < "3.8"
Provides-Extra: docs
Requires-Dist: sphinx-autoapi (==1.8.1) ; extra == 'docs'
Provides-Extra: flask
Requires-Dist: flask (<3,>=2) ; extra == 'flask'
Requires-Dist: a2wsgi (<2,>=1.1) ; extra == 'flask'
Provides-Extra: swagger-ui
Requires-Dist: swagger-ui-bundle (<0.1,>=0.0.2) ; extra == 'swagger-ui'
Provides-Extra: tests
Requires-Dist: decorator (<6,>=5) ; extra == 'tests'
Requires-Dist: pytest (<7,>=6) ; extra == 'tests'
Requires-Dist: pytest-cov (<3,>=2) ; extra == 'tests'
Requires-Dist: testfixtures (<7,>=6) ; extra == 'tests'
Requires-Dist: flask (<3,>=2) ; extra == 'tests'
Requires-Dist: a2wsgi (<2,>=1.1) ; extra == 'tests'
Requires-Dist: swagger-ui-bundle (<0.1,>=0.0.2) ; extra == 'tests'
